MANIFEST.in
setup.cfg
setup.py
betty/__init__.py
betty/celery.py
betty/wsgi.py
betty/authtoken/__init__.py
betty/authtoken/models.py
betty/authtoken/management/__init__.py
betty/authtoken/management/commands/__init__.py
betty/authtoken/management/commands/create_token.py
betty/authtoken/migrations/0001_initial.py
betty/authtoken/migrations/__init__.py
betty/conf/__init__.py
betty/conf/app.py
betty/conf/server.py
betty/conf/urls.py
betty/contrib/__init__.py
betty/contrib/cacheflush/__init__.py
betty/contrib/cacheflush/cachemaster.py
betty/cropper/__init__.py
betty/cropper/dssim.py
betty/cropper/flush.py
betty/cropper/middleware.py
betty/cropper/models.py
betty/cropper/storage.py
betty/cropper/tasks.py
betty/cropper/urls.py
betty/cropper/views.py
betty/cropper/api/__init__.py
betty/cropper/api/decorators.py
betty/cropper/api/urls.py
betty/cropper/api/views.py
betty/cropper/font/OpenSans-Semibold.ttf
betty/cropper/management/__init__.py
betty/cropper/management/commands/__init__.py
betty/cropper/management/commands/change_storage_root.py
betty/cropper/management/commands/make_disk_storage_paths_absolute.py
betty/cropper/management/commands/optimize_images.py
betty/cropper/migrations/0001_initial.py
betty/cropper/migrations/0001_squashed_0004_auto_20160317_1706.py
betty/cropper/migrations/0002_auto_20141203_2115.py
betty/cropper/migrations/0002_image_last_modified.py
betty/cropper/migrations/0003_image_jpeg_qualities.py
betty/cropper/migrations/0004_auto_20160317_1706.py
betty/cropper/migrations/__init__.py
betty/cropper/templates/image.js
betty/cropper/utils/__init__.py
betty/cropper/utils/http.py
betty/cropper/utils/placeholder.py
betty/cropper/utils/runner.py
betty/image_browser/__init__.py
betty/image_browser/urls.py
betty/image_browser/views.py
betty_cropper.egg-info/PKG-INFO
betty_cropper.egg-info/SOURCES.txt
betty_cropper.egg-info/dependency_links.txt
betty_cropper.egg-info/entry_points.txt
betty_cropper.egg-info/requires.txt
betty_cropper.egg-info/top_level.txt
requirements/common.txt
requirements/dev.txt
requirements/imgmin.txt
requirements/s3.txt