Metadata-Version: 1.0
Name: betty-cropper
Version: 2.6.1
Summary: A django-powered image server
Home-page: https://github.com/theonion/betty-cropper
Author: Chris Sinchok
Author-email: csinchok@theonion.com
License: MIT
Platform: UNKNOWN
